{
    "appKeys": {},
    "capabilities": [
        ""
    ],
    "companyName": "grrunnz@live.de",
    "longName": "SchiedsrichterApp",
    "projectType": "native",
    "resources": {
        "media": [
            {
                "file": "images/cross.png",
                "name": "CROSS",
                "targetPlatforms": null,
                "type": "bitmap"
            },
            {
                "file": "images/confirm.png",
                "name": "CONFIRM",
                "targetPlatforms": null,
                "type": "bitmap"
            },
            {
                "file": "images/tick.png",
                "name": "TICK",
                "targetPlatforms": null,
                "type": "bitmap"
            }
        ]
    },
    "sdkVersion": "3",
    "shortName": "SchiedsrichterApp",
    "targetPlatforms": [
        "basalt"
    ],
    "uuid": "508723dd-682d-41cb-a0fc-600701db505c",
    "versionLabel": "1.0",
    "watchapp": {
        "watchface": false
    }
}
